torchex/__init__.py
torchex/attribute/__init__.py
torchex/attribute/integrated_gradients.py
torchex/attribute/lime_interface.py
torchex/data/__init__.py
torchex/data/functional.py
torchex/data/transforms.py
torchex/data/datasets/__init__.py
torchex/data/datasets/utils.py
torchex/data/datasets/graph/__init__.py
torchex/data/datasets/graph/tox21.py
torchex/distributions/__init__.py
torchex/nn/__init__.py
torchex/nn/classifier.py
torchex/nn/init.py
torchex/nn/functional/__init__.py
torchex/nn/functional/cropping.py
torchex/nn/functional/local.py
torchex/nn/functional/masked_binary_cross_entropy.py
torchex/nn/functional/padding.py
torchex/nn/functional/util.py
torchex/nn/modules/__init__.py
torchex/nn/modules/cnn_blocks.py
torchex/nn/modules/conv.py
torchex/nn/modules/cordconv.py
torchex/nn/modules/cropping.py
torchex/nn/modules/dft.py
torchex/nn/modules/embedding.py
torchex/nn/modules/highway.py
torchex/nn/modules/inception.py
torchex/nn/modules/inceptionbn.py
torchex/nn/modules/local.py
torchex/nn/modules/loss.py
torchex/nn/modules/normalization.py
torchex/nn/modules/padding.py
torchex/nn/modules/pooling.py
torchex/nn/modules/string_to_module.py
torchex/nn/modules/util.py
torchex/nn/modules/graph/__init__.py
torchex/nn/modules/graph/batchnorm.py
torchex/nn/modules/graph/conv.py
torchex/nn/modules/graph/linear.py
torchex/nn/modules/graph/pooling.py
torchex/nn/modules/lazy/__init__.py
torchex/nn/modules/lazy/base.py
torchex/nn/modules/lazy/conv.py
torchex/nn/modules/lazy/linear.py
torchex/nn/modules/lazy/rnn.py
torchex/nn/modules/lazy/utils.py
torchex/nn/modules/rnn/__init__.py
torchex/nn/modules/rnn/basic.py
torchex/nn/modules/rnn/grud.py
torchex/nn/modules/rnn/indrnn.py
torchex/optim/__init__.py
torchex/utils/__init__.py
torchex/utils/complex_helper.py
torchex/utils/io.py
torchex/utils/tensorboard.py
torchex/utils/rnn/__init__.py
torchex/zoo/__init__.py
torchex/zoo/image_transformer_net.py
torchex/zoo/generative/__init__.py
torchex/zoo/rnn/__init__.py
torchex-0.0.16.dist-info/LICENCE
torchex-0.0.16.dist-info/METADATA
torchex-0.0.16.dist-info/WHEEL
torchex-0.0.16.dist-info/top_level.txt
torchex-0.0.16.dist-info/RECORD
