Metadata-Version: 2.1
Name: torchex
Version: 0.0.16
Summary: Pytorch Extension Module.
Home-page: https://github.com/0h-n0/torchex
Author: Koji Ono
Author-email: koji.ono@exwzd.com
License: UNKNOWN
Platform: UNKNOWN
Classifier: Programming Language :: Python :: 3.6
Requires-Python: >3.5
Requires-Dist: tensorboardx
Provides-Extra: docs
Requires-Dist: sphinx (>=1.4) ; extra == 'docs'
Requires-Dist: sphinx-rtd-theme ; extra == 'docs'
